nographs/__init__.py
nographs/_compatibility.py
nographs/_extra_edge_gadgets.py
nographs/_extra_matrix_gadgets.py
nographs/_extra_tsp.py
nographs/_gear_collections.py
nographs/_gears.py
nographs/_path.py
nographs/_paths.py
nographs/_types.py
nographs/py.typed
nographs/_strategies/__init__.py
nographs/_strategies/strategy.py
nographs/_strategies/type_aliases.py
nographs/_strategies/utils.py
nographs/_strategies/bidirectional_search/__init__.py
nographs/_strategies/bidirectional_search/base.py
nographs/_strategies/bidirectional_search/breadth_first.py
nographs/_strategies/bidirectional_search/shortest_path.py
nographs/_strategies/traversals/__init__.py
nographs/_strategies/traversals/traversal.py
nographs/_strategies/traversals/with_weights/__init__.py
nographs/_strategies/traversals/with_weights/a_star.py
nographs/_strategies/traversals/with_weights/extra_infinite_branching.py
nographs/_strategies/traversals/with_weights/minimum_spanning_tree.py
nographs/_strategies/traversals/with_weights/shortest_paths.py
nographs/_strategies/traversals/with_weights/traversal_with_weights.py
nographs/_strategies/traversals/without_weights/__init__.py
nographs/_strategies/traversals/without_weights/breadth_first.py
nographs/_strategies/traversals/without_weights/depth_first.py
nographs/_strategies/traversals/without_weights/depth_first_enum_types.py
nographs/_strategies/traversals/without_weights/neighbors_then_depth.py
nographs/_strategies/traversals/without_weights/topological_sort.py
nographs/_strategies/traversals/without_weights/traversal_without_weights.py
nographs-3.4.3.dist-info/licenses/LICENSE
nographs-3.4.3.dist-info/METADATA
nographs-3.4.3.dist-info/WHEEL
nographs-3.4.3.dist-info/top_level.txt
nographs-3.4.3.dist-info/RECORD
