Metadata-Version: 2.4
Name: nographs
Version: 3.4.3
Summary: Graph analysis – the lazy (evaluation) way: Analysis on the fly, for implicit graphs, that are computed and/or adapted on the fly.
Author-email: "Dr. Helmut Melcher" <HeWeMel@web.de>
License-Expression: MIT
Project-URL: Homepage, https://github.com/hewemel/nographs
Project-URL: Documentation, https://nographs.readthedocs.io/
Project-URL: Repository, https://github.com/hewemel/nographs.git
Project-URL: Issues, https://github.com/hewemel/nographs/issues
Project-URL: Changelog, https://nographs.readthedocs.io/en/latest/changelog.html
Keywords: graph,network,search,traverse,analysis,infinite,lazy,shortest,distance,depth,DFS,breadth,BFS,Dijkstra,topological,spanning,MST,TSP
Classifier: Development Status :: 5 - Production/Stable
Classifier: Programming Language :: Python :: 3
Classifier: Programming Language :: Python :: 3.9
Classifier: Programming Language :: Python :: 3.10
Classifier: Programming Language :: Python :: 3.11
Classifier: Programming Language :: Python :: 3.12
Classifier: Programming Language :: Python :: 3.13
Classifier: Programming Language :: Python :: 3.14
Classifier: Programming Language :: Python :: Implementation :: CPython
Classifier: Programming Language :: Python :: Implementation :: PyPy
Classifier: Intended Audience :: Developers
Classifier: Intended Audience :: Science/Research
Classifier: Operating System :: OS Independent
Classifier: Topic :: Scientific/Engineering :: Information Analysis
Classifier: Topic :: Scientific/Engineering :: Mathematics
Classifier: Topic :: Software Development :: Libraries :: Python Modules
Classifier: Typing :: Typed
Requires-Python: >=3.9
License-File: LICENSE
Dynamic: license-file
